setup.py
remote_fixtures/__init__.py
remote_fixtures/conf.py
remote_fixtures/models.py
remote_fixtures/tests.py
remote_fixtures/utils.py
remote_fixtures.egg-info/PKG-INFO
remote_fixtures.egg-info/SOURCES.txt
remote_fixtures.egg-info/dependency_links.txt
remote_fixtures.egg-info/requires.txt
remote_fixtures.egg-info/top_level.txt
remote_fixtures/management/__init__.py
remote_fixtures/management/commands/__init__.py
remote_fixtures/management/commands/list_fixtures.py
remote_fixtures/management/commands/pull_fixtures.py
remote_fixtures/management/commands/push_fixtures.py