Metadata-Version: 1.0
Name: remote-fixtures
Version: 0.4.1
Summary: Django remote fixture loading
Home-page: https://github.com/gizmag/remote-fixtures
Author: Gizmag
Author-email: tech@gizmag.com
License: UNKNOWN
Platform: UNKNOWN
